{
  "files": [
    {
      "path": "src-tauri/src/types.rs",
      "content": "use serde::{Deserialize, Serialize};\nuse std::collections::HashMap;\n\n#[derive(Debug, Clone, Serialize, Deserialize)]\npub struct Point3D {\n    pub x: f64,\n    pub y: f64,\n    pub z: f64,\n}\n\n#[derive(Debug, Clone, Serialize, Deserialize)]\npub enum AntennaError {\n    InvalidGeometry,\n    SimulationFailed,\n    InvalidParameter,\n    NumericalError,\n}\n\n#[derive(Debug, Clone, Serialize, Deserialize)]\npub struct Material {\n    pub name: String,\n    pub epsilon_r: f64,\n    pub mu_r: f64,\n    pub sigma: f64,\n    pub tan_delta: f64,\n}\n\n#[derive(Debug, Clone, Serialize, Deserialize)]\npub enum UnitSystem {\n    Metric,\n    Imperial,\n}\n\n#[derive(Debug, Clone, Serialize, Deserialize)]\npub enum LengthUnit {\n    Meters,\n    Centimeters,\n    Millimeters,\n    Inches,\n}\n\n#[derive(Debug, Clone, Serialize, Deserialize)]\npub enum FrequencyUnit {\n    Hz,\n    KHz,\n    MHz,\n    GHz,\n}\n\n#[derive(Debug, Clone, Serialize, Deserialize)]\npub struct GPUCapabilities {\n    pub available: bool,\n    pub device_name: String,\n    pub memory_mb: u64,\n    pub compute_units: u32,\n    pub supports_compute: bool,\n}\n\n#[derive(Debug, Clone, Serialize, Deserialize)]\npub struct BenchmarkResult {\n    pub matrix_size: usize,\n    pub cpu_time_ms: f64,\n    pub gpu_time_ms: f64,\n    pub speedup_ratio: f64,\n    pub memory_used_mb: f64,\n}\n\n#[derive(Debug, Clone, Serialize, Deserialize)]\npub struct ModelPrediction {\n    pub s_parameters: Vec<SParameterResult>,\n    pub confidence: f64,\n    pub uncertainty: Option<f64>,\n    pub inference_time_ms: f64,\n    pub model_version: String,\n}\n\n#[derive(Debug, Clone, Serialize, Deserialize)]\npub struct OptimizationResult {\n    pub optimal_parameters: HashMap<String, f64>,\n    pub achieved_s11_db: f64,\n    pub target_frequency: f64,\n    pub generations: u32,\n    pub convergence_history: Vec<f64>,\n    pub optimization_time_ms: f64,\n}\n\n#[derive(Debug, Clone, Serialize, Deserialize)]\npub struct ProjectData {\n    pub name: String,\n    pub version: String,\n    pub created_at: String,\n    pub modified_at: String,\n    pub antenna_type: String,\n    pub parameters: HashMap<String, f64>,\n    pub simulation_results: Option<SimulationResult>,\n    pub optimization_results: Option<OptimizationResult>,\n    pub materials: Vec<Material>,\n    pub unit_system: UnitSystem,\n}\n\n// Forward declarations for types defined in other modules\nuse crate::solver::SParameterResult;\nuse crate::solver::SimulationResult;"
    },
    {
      "path": "src-tauri/src/element.rs",
      "content": "use serde::{Deserialize, Serialize};\nuse crate::types::Point3D;\n\n#[derive(Debug, Clone, Serialize, Deserialize)]\npub struct DipoleParams {\n    pub length: f64,\n    pub radius: f64,\n    pub center: Point3D,\n    pub orientation: Point3D,\n}\n\n#[derive(Debug, Clone, Serialize, Deserialize)]\npub struct PatchParams {\n    pub width: f64,\n    pub length: f64,\n    pub substrate_height: f64,\n    pub substrate_er: f64,\n    pub center: Point3D,\n}\n\n#[derive(Debug, Clone, Serialize, Deserialize)]\npub struct QfhParams {\n    pub frequency: f64,\n    pub turns: f64,\n    pub diameter: f64,\n    pub height: f64,\n    pub wire_radius: f64,\n    pub center: Point3D,\n}\n\n#[derive(Debug, Clone, Serialize, Deserialize)]\npub struct MonopoleParams {\n    pub length: f64,\n    pub radius: f64,\n    pub ground_plane_radius: f64,\n    pub center: Point3D,\n}\n\n#[derive(Debug, Clone, Serialize, Deserialize)]\npub struct YagiParams {\n    pub reflector_length: f64,\n    pub driven_length: f64,\n    pub director_length: f64,\n    pub element_spacing: f64,\n    pub wire_radius: f64,\n    pub center: Point3D,\n}\n\n#[derive(Debug, Clone, Serialize, Deserialize)]\npub enum AntennaElement {\n    Dipole(DipoleParams),\n    Patch(PatchParams),\n    Qfh(QfhParams),\n    Monopole(MonopoleParams),\n    Yagi(YagiParams),\n}\n\npub trait AntennaGeometry {\n    fn get_segments(&self) -> Vec<Point3D>;\n    fn get_feed_points(&self) -> Vec<Point3D>;\n    fn get_bounding_box(&self) -> (Point3D, Point3D);\n    fn validate_parameters(&self) -> Result<(), crate::types::AntennaError>;\n    fn get_resonant_frequency(&self) -> f64;\n}"
    },
    {
      "path": "src-tauri/src/solver.rs",
      "content": "use serde::{Deserialize, Serialize};\nuse crate::types::Point3D;\n\n#[derive(Debug, Clone, Serialize, Deserialize)]\npub struct SimulationParams {\n    pub frequency: f64,\n    pub resolution: usize,\n    pub reference_impedance: f64,\n}\n\n#[derive(Debug, Clone, Serialize, Deserialize)]\npub struct SimulationConfig {\n    pub start_frequency: f64,\n    pub stop_frequency: f64,\n    pub num_points: usize,\n    pub reference_impedance: f64,\n    pub use_gpu: bool,\n    pub solver_type: String,\n    pub convergence_threshold: f64,\n}\n\n#[derive(Debug, Clone, Serialize, Deserialize)]\npub struct SParameterResult {\n    pub frequency: f64,\n    pub s11_re: f64,\n    pub s11_im: f64,\n    pub vswr: f64,\n    pub input_impedance_re: f64,\n    pub input_impedance_im: f64,\n}\n\n#[derive(Debug, Clone, Serialize, Deserialize)]\npub struct FieldResult {\n    pub points: Vec<Point3D>,\n    pub e_field: Vec<Point3D>,\n    pub h_field: Vec<Point3D>,\n    pub power_density: Vec<f64>,\n}\n\n#[derive(Debug, Clone, Serialize, Deserialize)]\npub struct RadiationPattern {\n    pub theta: Vec<f64>,\n    pub phi: Vec<f64>,\n    pub gain_db: Vec<Vec<f64>>,\n    pub directivity_db: f64,\n    pub efficiency: f64,\n}\n\n#[derive(Debug, Clone, Serialize, Deserialize)]\npub struct SimulationResult {\n    pub s_params: Vec<SParameterResult>,\n    pub field: Option<FieldResult>,\n    pub radiation_pattern: Option<RadiationPattern>,\n    pub num_unknowns: usize,\n    pub solver_type: String,\n    pub computation_time_ms: f64,\n    pub memory_used_mb: f64,\n}\n\n#[derive(Debug, Clone, Serialize, Deserialize)]\npub struct SimulationProgress {\n    pub stage: String,\n    pub progress: f64,\n    pub eta_seconds: Option<f64>,\n    pub current_frequency: Option<f64>,\n}"
    },
    {
      "path": "src-tauri/src/bridge.rs",
      "content": "use tauri::command;\nuse serde_json::Value;\nuse crate::types::*;\nuse crate::solver::*;\nuse crate::element::*;\n\n#[command]\npub async fn create_antenna(params: Value) -> Result<String, String> {\n    // Implementation will deserialize params to AntennaElement\n    // and return serialized antenna ID or geometry\n    Ok(\"antenna_created\".to_string())\n}\n\n#[command]\npub async fn run_simulation(config: Value) -> Result<String, String> {\n    // Implementation will deserialize config to SimulationConfig\n    // and return serialized SimulationResult\n    Ok(\"simulation_complete\".to_string())\n}\n\n#[command]\npub async fn get_simulation_status() -> Result<String, String> {\n    // Implementation will return serialized SimulationProgress\n    Ok(\"simulation_running\".to_string())\n}\n\n#[command]\npub async fn load_touchstone(path: String) -> Result<String, String> {\n    // Implementation will parse .s1p/.s2p file\n    // and return serialized Vec<SParameterResult>\n    Ok(\"touchstone_loaded\".to_string())\n}\n\n#[command]\npub async fn save_project(path: String, data: Value) -> Result<String, String> {\n    // Implementation will serialize ProjectData to JSON file\n    Ok(\"project_saved\".to_string())\n}\n\n#[command]\npub async fn load_project(path: String) -> Result<String, String> {\n    // Implementation will deserialize JSON file to ProjectData\n    Ok(\"project_loaded\".to_string())\n}\n\n#[command]\npub async fn get_gpu_capabilities() -> Result<String, String> {\n    // Implementation will return serialized GPUCapabilities\n    Ok(\"gpu_detected\".to_string())\n}\n\n#[command]\npub async fn run_benchmark(matrix_sizes: Vec<usize>) -> Result<String, String> {\n    // Implementation will return serialized Vec<BenchmarkResult>\n    Ok(\"benchmark_complete\".to_string())\n}\n\n#[command]\npub async fn predict_with_ai(params: Value) -> Result<String, String> {\n    // Implementation will return serialized ModelPrediction\n    Ok(\"prediction_complete\".to_string())\n}\n\n#[command]\npub async fn optimize_antenna(config: Value) -> Result<String, String> {\n    // Implementation will return serialized OptimizationResult\n    Ok(\"optimization_complete\".to_string())\n}\n\n#[command]\npub async fn export_touchstone(results: Value, path: String) -> Result<String, String> {\n    // Implementation will write Vec<SParameterResult> to .s1p file\n    Ok(\"touchstone_exported\".to_string())\n}\n\n#[command]\npub async fn generate_report(project_data: Value, path: String) -> Result<String, String> {\n    // Implementation will generate PDF report from ProjectData\n    Ok(\"report_generated\".to_string())\n}"
    },
    {
      "path": "src/types/antenna.ts",
      "content": "export interface Point3D {\n  x: number;\n  y: number;\n  z: number;\n}\n\nexport interface Material {\n  name: string;\n  epsilonR: number;\n  muR: number;\n  sigma: number;\n  tanDelta: number;\n}\n\nexport enum UnitSystem {\n  Metric = 'Metric',\n  Imperial = 'Imperial'\n}\n\nexport enum LengthUnit {\n  Meters = 'Meters',\n  Centimeters = 'Centimeters',\n  Millimeters = 'Millimeters',\n  Inches = 'Inches'\n}\n\nexport enum FrequencyUnit {\n  Hz = 'Hz',\n  KHz = 'KHz',\n  MHz = 'MHz',\n  GHz = 'GHz'\n}\n\nexport interface DipoleParams {\n  length: number;\n  radius: number;\n  center: Point3D;\n  orientation: Point3D;\n}\n\nexport interface PatchParams {\n  width: number;\n  length: number;\n  substrateHeight: number;\n  substrateEr: number;\n  center: Point3D;\n}\n\nexport interface QfhParams {\n  frequency: number;\n  turns: number;\n  diameter: number;\n  height: number;\n  wireRadius: number;\n  center: Point3D;\n}\n\nexport interface MonopoleParams {\n  length: number;\n  radius: number;\n  groundPlaneRadius: number;\n  center: Point3D;\n}\n\nexport interface YagiParams {\n  reflectorLength: number;\n  drivenLength: number;\n  directorLength: number;\n  elementSpacing: number;\n  wireRadius: number;\n  center: Point3D;\n}\n\nexport type AntennaType = 'Dipole' | 'Patch' | 'Qfh' | 'Monopole' | 'Yagi';\n\nexport type AntennaParams = DipoleParams | PatchParams | QfhParams | MonopoleParams | YagiParams;\n\nexport interface AntennaElement {\n  type: AntennaType;\n  params: AntennaParams;\n}\n\nexport enum AntennaError {\n  InvalidGeometry = 'InvalidGeometry',\n  SimulationFailed = 'SimulationFailed',\n  InvalidParameter = 'InvalidParameter',\n  NumericalError = 'NumericalError'\n}"
    },
    {
      "path": "src/types/simulation.ts",
      "content": "import { Point3D } from './antenna';\n\nexport interface SimulationParams {\n  frequency: number;\n  resolution: number;\n  referenceImpedance: number;\n}\n\nexport interface SimulationConfig {\n  startFrequency: number;\n  stopFrequency: number;\n  numPoints: number;\n  referenceImpedance: number;\n  useGpu: boolean;\n  solverType: string;\n  convergenceThreshold: number;\n}\n\nexport interface SParameterResult {\n  frequency: number;\n  s11Re: number;\n  s11Im: number;\n  vswr: number;\n  inputImpedanceRe: number;\n  inputImpedanceIm: number;\n}\n\nexport interface FieldResult {\n  points: Point3D[];\n  eField: Point3D[];\n  hField: Point3D[];\n  powerDensity: number[];\n}\n\nexport interface RadiationPattern {\n  theta: number[];\n  phi: number[];\n  gainDb: number[][];\n  directivityDb: number;\n  efficiency: number;\n}\n\nexport interface SimulationResult {\n  sParams: SParameterResult[];\n  field?: FieldResult;\n  radiationPattern?: RadiationPattern;\n  numUnknowns: number;\n  solverType: string;\n  computationTimeMs: number;\n  memoryUsedMb: number;\n}\n\nexport interface SimulationProgress {\n  stage: string;\n  progress: number;\n  etaSeconds?: number;\n  currentFrequency?: number;\n}\n\nexport interface GPUCapabilities {\n  available: boolean;\n  deviceName: string;\n  memoryMb: number;\n  computeUnits: number;\n  supportsCompute: boolean;\n}\n\nexport interface BenchmarkResult {\n  matrixSize: number;\n  cpuTimeMs: number;\n  gpuTimeMs: number;\n  speedupRatio: number;\n  memoryUsedMb: number;\n}\n\nexport interface ModelPrediction {\n  sParameters: SParameterResult[];\n  confidence: number;\n  uncertainty?: number;\n  inferenceTimeMs: number;\n  modelVersion: string;\n}\n\nexport interface OptimizationResult {\n  optimalParameters: Record<string, number>;\n  achievedS11Db: number;\n  targetFrequency: number;\n  generations: number;\n  convergenceHistory: number[];\n  optimizationTimeMs: number;\n}\n\nexport interface ProjectData {\n  name: string;\n  version: string;\n  createdAt: string;\n  modifiedAt: string;\n  antennaType: string;\n  parameters: Record<string, number>;\n  simulationResults?: SimulationResult;\n  optimizationResults?: OptimizationResult;\n  materials: import('./antenna').Material[];\n  unitSystem: import('./antenna').UnitSystem;\n}"
    },
    {
      "path": "python/antenna_ml/types.py",
      "content": "from pydantic import BaseModel\nfrom typing import List, Optional, Dict, Union\nfrom enum import Enum\n\nclass Point3D(BaseModel):\n    x: float\n    y: float\n    z: float\n\nclass Material(BaseModel):\n    name: str\n    epsilon_r: float\n    mu_r: float\n    sigma: float\n    tan_delta: float\n\nclass UnitSystem(str, Enum):\n    METRIC = \"Metric\"\n    IMPERIAL = \"Imperial\"\n\nclass LengthUnit(str, Enum):\n    METERS = \"Meters\"\n    CENTIMETERS = \"Centimeters\"\n    MILLIMETERS = \"Millimeters\"\n    INCHES = \"Inches\"\n\nclass FrequencyUnit(str, Enum):\n    HZ = \"Hz\"\n    KHZ = \"KHz\"\n    MHZ = \"MHz\"\n    GHZ = \"GHz\"\n\nclass DipoleParams(BaseModel):\n    length: float\n    radius: float\n    center: Point3D\n    orientation: Point3D\n\nclass PatchParams(BaseModel):\n    width: float\n    length: float\n    substrate_height: float\n    substrate_er: float\n    center: Point3D\n\nclass QfhParams(BaseModel):\n    frequency: float\n    turns: float\n    diameter: float\n    height: float\n    wire_radius: float\n    center: Point3D\n\nclass MonopoleParams(BaseModel):\n    length: float\n    radius: float\n    ground_plane_radius: float\n    center: Point3D\n\nclass YagiParams(BaseModel):\n    reflector_length: float\n    driven_length: float\n    director_length: float\n    element_spacing: float\n    wire_radius: float\n    center: Point3D\n\nAntennaParameters = Union[DipoleParams, PatchParams, QfhParams, MonopoleParams, YagiParams]\n\nclass SParameterResult(BaseModel):\n    frequency: float\n    s11_re: float\n    s11_im: float\n    vswr: float\n    input_impedance_re: float\n    input_impedance_im: float\n\nclass FieldResult(BaseModel):\n    points: List[Point3D]\n    e_field: List[Point3D]\n    h_field: List[Point3D]\n    power_density: List[float]\n\nclass RadiationPattern(BaseModel):\n    theta: List[float]\n    phi: List[float]\n    gain_db: List[List[float]]\n    directivity_db: float\n    efficiency: float\n\nclass SimulationResult(BaseModel):\n    s_params: List[SParameterResult]\n    field: Optional[FieldResult] = None\n    radiation_pattern: Optional[RadiationPattern] = None\n    num_unknowns: int\n    solver_type: str\n    computation_time_ms: float\n    memory_used_mb: float\n\nclass TrainingDataset(BaseModel):\n    antenna_type: str\n    parameters: List[Dict[str, float]]\n    s_parameter_results: List[List[SParameterResult]]\n    metadata: Dict[str, Union[str, float, int]]\n\nclass ModelConfig(BaseModel):\n    model_type: str\n    input_features: List[str]\n    output_features: List[str]\n    hidden_layers: List[int]\n    learning_rate: float\n    batch_size: int\n    epochs: int\n    validation_split: float\n\nclass ModelPrediction(BaseModel):\n    s_parameters: List[SParameterResult]\n    confidence: float\n    uncertainty: Optional[float] = None\n    inference_time_ms: float\n    model_version: str\n\nclass OptimizationConfig(BaseModel):\n    target_frequency: float\n    target_s11_db: float\n    parameter_bounds: Dict[str, tuple[float, float]]\n    population_size: int\n    mutation_rate: float\n    crossover_rate: float\n    max_generations: int\n\nclass OptimizationResult(BaseModel):\n    optimal_parameters: Dict[str, float]\n    achieved_s11_db: float\n    target_frequency: float\n    generations: int\n    convergence_history: List[float]\n    optimization_time_ms: float"
    },
    {
      "path": "src-tauri/src/materials.rs",
      "content": "use serde::{Deserialize, Serialize};\nuse crate::types::Material;\nuse std::collections::HashMap;\n\n#[derive(Debug, Clone, Serialize, Deserialize)]\npub struct MaterialDatabase {\n    pub materials: HashMap<String, Material>,\n}\n\nimpl MaterialDatabase {\n    pub fn new() -> Self {\n        let mut materials = HashMap::new();\n        \n        // Perfect Electric Conductor\n        materials.insert(\"PEC\".to_string(), Material {\n            name: \"Perfect Electric Conductor\".to_string(),\n            epsilon_r: 1.0,\n            mu_r: 1.0,\n            sigma: 1e10,\n            tan_delta: 0.0,\n        });\n        \n        // Copper\n        materials.insert(\"Copper\".to_string(), Material {\n            name: \"Copper\".to_string(),\n            epsilon_r: 1.0,\n            mu_r: 1.0,\n            sigma: 5.96e7,\n            tan_delta: 0.0,\n        });\n        \n        // FR4 Substrate\n        materials.insert(\"FR4\".to_string(), Material {\n            name: \"FR4 Substrate\".to_string(),\n            epsilon_r: 4.4,\n            mu_r: 1.0,\n            sigma: 0.0,\n            tan_delta: 0.02,\n        });\n        \n        // Air/Vacuum\n        materials.insert(\"Air\".to_string(), Material {\n            name: \"Air\".to_string(),\n            epsilon_r: 1.0,\n            mu_r: 1.0,\n            sigma: 0.0,\n            tan_delta: 0.0,\n        });\n        \n        // Rogers RT/duroid 5880\n        materials.insert(\"RT5880\".to_string(), Material {\n            name: \"Rogers RT/duroid 5880\".to_string(),\n            epsilon_r: 2.2,\n            mu_r: 1.0,\n            sigma: 0.0,\n            tan_delta: 0.0009,\n        });\n        \n        Self { materials }\n    }\n    \n    pub fn get_material(&self, name: &str) -> Option<&Material> {\n        self.materials.get(name)\n    }\n    \n    pub fn add_material(&mut self, material: Material) {\n        self.materials.insert(material.name.clone(), material);\n    }\n    \n    pub fn list_materials(&self) -> Vec<&String> {\n        self.materials.keys().collect()\n    }\n}"
    },
    {
      "path": "src/types/materials.ts",
      "content": "import { Material } from './antenna';\n\nexport interface MaterialDatabase {\n  materials: Record<string, Material>;\n}\n\nexport const DEFAULT_MATERIALS: Record<string, Material> = {\n  PEC: {\n    name: 'Perfect Electric Conductor',\n    epsilonR: 1.0,\n    muR: 1.0,\n    sigma: 1e10,\n    tanDelta: 0.0\n  },\n  Copper: {\n    name: 'Copper',\n    epsilonR: 1.0,\n    muR: 1.0,\n    sigma: 5.96e7,\n    tanDelta: 0.0\n  },\n  FR4: {\n    name: 'FR4 Substrate',\n    epsilonR: 4.4,\n    muR: 1.0,\n    sigma: 0.0,\n    tanDelta: 0.02\n  },\n  Air: {\n    name: 'Air',\n    epsilonR: 1.0,\n    muR: 1.0,\n    sigma: 0.0,\n    tanDelta: 0.0\n  },\n  RT5880: {\n    name: 'Rogers RT/duroid 5880',\n    epsilonR: 2.2,\n    muR: 1.0,\n    sigma: 0.0,\n    tanDelta: 0.0009\n  }\n};\n\nexport class MaterialManager {\n  private materials: Record<string, Material>;\n  \n  constructor(initialMaterials: Record<string, Material> = DEFAULT_MATERIALS) {\n    this.materials = { ...initialMaterials };\n  }\n  \n  getMaterial(name: string): Material | undefined {\n    return this.materials[name];\n  }\n  \n  addMaterial(material: Material): void {\n    this.materials[material.name] = material;\n  }\n  \n  listMaterials(): string[] {\n    return Object.keys(this.materials);\n  }\n  \n  getAllMaterials(): Record<string, Material> {\n    return { ...this.materials };\n  }\n}"
    },
    {
      "path": "python/antenna_ml/materials.py",
      "content": "from typing import Dict, Optional\nfrom .types import Material\n\nDEFAULT_MATERIALS: Dict[str, Material] = {\n    \"PEC\": Material(\n        name=\"Perfect Electric Conductor\",\n        epsilon_r=1.0,\n        mu_r=1.0,\n        sigma=1e10,\n        tan_delta=0.0\n    ),\n    \"Copper\": Material(\n        name=\"Copper\",\n        epsilon_r=1.0,\n        mu_r=1.0,\n        sigma=5.96e7,\n        tan_delta=0.0\n    ),\n    \"FR4\": Material(\n        name=\"FR4 Substrate\",\n        epsilon_r=4.4,\n        mu_r=1.0,\n        sigma=0.0,\n        tan_delta=0.02\n    ),\n    \"Air\": Material(\n        name=\"Air\",\n        epsilon_r=1.0,\n        mu_r=1.0,\n        sigma=0.0,\n        tan_delta=0.0\n    ),\n    \"RT5880\": Material(\n        name=\"Rogers RT/duroid 5880\",\n        epsilon_r=2.2,\n        mu_r=1.0,\n        sigma=0.0,\n        tan_delta=0.0009\n    )\n}\n\nclass MaterialDatabase:\n    def __init__(self, materials: Optional[Dict[str, Material]] = None):\n        self.materials = materials or DEFAULT_MATERIALS.copy()\n    \n    def get_material(self, name: str) -> Optional[Material]:\n        return self.materials.get(name)\n    \n    def add_material(self, material: Material) -> None:\n        self.materials[material.name] = material\n    \n    def list_materials(self) -> list[str]:\n        return list(self.materials.keys())\n    \n    def get_all_materials(self) -> Dict[str, Material]:\n        return self.materials.copy()"
    },
    {
      "path": "src-tauri/src/lib.rs",
      "content": "pub mod types;\npub mod element;\npub mod solver;\npub mod bridge;\npub mod materials;\npub mod core;\npub mod gpu;\n\nuse tauri::Manager;\n\n#[cfg_attr(mobile, tauri::mobile_entry_point)]\npub fn run() {\n    tauri::Builder::default()\n        .plugin(tauri_plugin_shell::init())\n        .invoke_handler(tauri::generate_handler![\n            bridge::create_antenna,\n            bridge::run_simulation,\n            bridge::get_simulation_status,\n            bridge::load_touchstone,\n            bridge::save_project,\n            bridge::load_project,\n            bridge::get_gpu_capabilities,\n            bridge::run_benchmark,\n            bridge::predict_with_ai,\n            bridge::optimize_antenna,\n            bridge::export_touchstone,\n            bridge::generate_report\n        ])\n        .setup(|app| {\n            // Initialize material database\n            let materials = materials::MaterialDatabase::new();\n            app.manage(materials);\n            Ok(())\n        })\n        .run(tauri::generate_context!())\n        .expect(\"error while running tauri application\");\n}"
    },
    {
      "path": "src/hooks/useTauri.ts",
      "content": "import { invoke } from '@tauri-apps/api/tauri';\nimport { listen } from '@tauri-apps/api/event';\nimport { useCallback, useEffect, useState } from 'react';\nimport type { \n  SimulationResult, \n  SimulationProgress, \n  ProjectData,\n  GPUCapabilities,\n  BenchmarkResult,\n  ModelPrediction,\n  OptimizationResult\n} from '../types/simulation';\nimport type { AntennaElement } from '../types/antenna';\n\nexport const useTauri = () => {\n  const [simulationProgress, setSimulationProgress] = useState<SimulationProgress | null>(null);\n  const [isSimulating, setIsSimulating] = useState(false);\n\n  useEffect(() => {\n    const unlistenProgress = listen<SimulationProgress>('simulation_progress', (event) => {\n      setSimulationProgress(event.payload);\n    });\n\n    const unlistenComplete = listen<SimulationResult>('simulation_complete', (event) => {\n      setIsSimulating(false);\n      setSimulationProgress(null);\n    });\n\n    const unlistenError = listen<string>('simulation_error', (event) => {\n      setIsSimulating(false);\n      setSimulationProgress(null);\n      console.error('Simulation error:', event.payload);\n    });\n\n    return () => {\n      unlistenProgress.then(fn => fn());\n      unlistenComplete.then(fn => fn());\n      unlistenError.then(fn => fn());\n    };\n  }, []);\n\n  const createAntenna = useCallback(async (params: AntennaElement): Promise<string> => {\n    return await invoke<string>('create_antenna', { params });\n  }, []);\n\n  const runSimulation = useCallback(async (config: any): Promise<SimulationResult> => {\n    setIsSimulating(true);\n    const result = await invoke<string>('run_simulation', { config });\n    return JSON.parse(result);\n  }, []);\n\n  const loadTouchstone = useCallback(async (path: string): Promise<any> => {\n    const result = await invoke<string>('load_touchstone', { path });\n    return JSON.parse(result);\n  }, []);\n\n  const saveProject = useCallback(async (path: string, data: ProjectData): Promise<void> => {\n    await invoke<string>('save_project', { path, data });\n  }, []);\n\n  const loadProject = useCallback(async (path: string): Promise<ProjectData> => {\n    const result = await invoke<string>('load_project', { path });\n    return JSON.parse(result);\n  }, []);\n\n  const getGpuCapabilities = useCallback(async (): Promise<GPUCapabilities> => {\n    const result = await invoke<string>('get_gpu_capabilities');\n    return JSON.parse(result);\n  }, []);\n\n  const runBenchmark = useCallback(async (matrixSizes: number[]): Promise<BenchmarkResult[]> => {\n    const result = await invoke<string>('run_benchmark', { matrixSizes });\n    return JSON.parse(result);\n  }, []);\n\n  const predictWithAi = useCallback(async (params: any): Promise<ModelPrediction> => {\n    const result = await invoke<string>('predict_with_ai', { params });\n    return JSON.parse(result);\n  }, []);\n\n  const optimizeAntenna = useCallback(async (config: any): Promise<OptimizationResult> => {\n    const result = await invoke<string>('optimize_antenna', { config });\n    return JSON.parse(result);\n  }, []);\n\n  const exportTouchstone = useCallback(async (results: any, path: string): Promise<void> => {\n    await invoke<string>('export_touchstone', { results, path });\n  }, []);\n\n  const generateReport = useCallback(async (projectData: ProjectData, path: string): Promise<void> => {\n    await invoke<string>('generate_report', { projectData, path });\n  }, []);\n\n  return {\n    createAntenna,\n    runSimulation,\n    loadTouchstone,\n    saveProject,\n    loadProject,\n    getGpuCapabilities,\n    runBenchmark,\n    predictWithAi,\n    optimizeAntenna,\n    exportTouchstone,\n    generateReport,\n    simulationProgress,\n    isSimulating\n  };\n};"
    }
  ],
  "conventions": {
    "architectural_decisions": {
      "simulation_phase_1": "Method of Moments (MoM) frequency-domain solver for wire and surface antennas with Z-matrix fill, LU solve for currents, S-parameter extraction, and far-field computation",
      "python_rust_bridge": "ONNX Runtime for inference - PyTorch training in Python, ONNX export, Rust inference via 'ort' crate with no Python runtime in production",
      "material_database": "JSON file loaded at startup with required materials: PEC, copper, FR4, air/vacuum. Material struct contains name, epsilon_r, mu_r, sigma, tan_delta",
      "units_system": "Internal SI units (meters, Hz, seconds) with configurable display units (mm/cm/in, MHz/GHz). UnitSystem enum shared across Rust/TS/Python",
      "project_file_format": ".promin extension containing JSON with antenna params, sim config, material assignments, and results",
      "state_management": "Tauri commands for core operations, Tauri events for progress/completion, React context + useReducer for frontend state",
      "test_fixtures": "Analytical half-wave dipole validation (73+j42.5Ω), GPU vs CPU matrix operations, UI snapshot tests, 3D render tests, ONNX roundtrip validation"
    },
    "type_system": {
      "source_of_truth": "Rust types are canonical - all TypeScript and Python types mirror Rust exactly",
      "naming_convention": "snake_case in Rust/Python, camelCase in TypeScript, identical field names across languages",
      "serialization": "serde for Rust, JSON for inter-language communication, Pydantic for Python validation",
      "error_handling": "Result<T, AntennaError> in Rust, proper error propagation to frontend with user-friendly messages"
    },
    "shared_interfaces": {
      "antenna_geometry": "AntennaGeometry trait implemented by all antenna types for segments, feed points, bounding box, validation",
      "simulation_data": "SParameterResult, SimulationResult, SimulationProgress structs shared across all teams",
      "gpu_integration": "GPUCapabilities, BenchmarkResult structs for hardware detection and performance metrics",
      "ai_integration": "ModelPrediction, OptimizationResult structs for AI inference and optimization results",
      "project_management": "ProjectData struct for complete project serialization including antenna, results, materials"
    },
    "team_boundaries": {
      "core_team": "Rust simulation engine, antenna models, MoM solver, material database, project management",
      "gpu_team": "wgpu compute shaders, GPU acceleration, performance benchmarking, memory management",
      "ui_team": "React components, parameter controls, charts, project interface, Tauri integration",
      "3d_team": "Three.js viewport, antenna visualization, field rendering, radiation patterns",
      "aiml_team": "PyTorch training, ONNX export, dataset generation, model evaluation, Python utilities"
    }
  }
}